phantomwright/__init__.py
phantomwright/_repo_version.py
phantomwright/py.typed
phantomwright/_impl/__init__.py
phantomwright/_impl/_core_debug_patch.py
phantomwright/_impl/_evaluate_patch.py
phantomwright/_impl/_inconsistency_patch.py
phantomwright/async_api/__init__.py
phantomwright/captcha/__init__.py
phantomwright/captcha/test.py
phantomwright/captcha/cloudfare/solver.py
phantomwright/captcha/cloudfare/scripts/observer.js
phantomwright/captcha/cloudfare/scripts/shadow_root.js
phantomwright/captcha/cloudfare/utils/build_js.py
phantomwright/captcha/cloudfare/utils/consts.py
phantomwright/captcha/cloudfare/utils/detection.py
phantomwright/captcha/cloudfare/utils/dom_helpers.py
phantomwright/captcha/cloudfare/utils/shadow_root.py
phantomwright/stealth/__init__.py
phantomwright/stealth/stealth.py
phantomwright/stealth/js/generate.magic.arrays.js
phantomwright/stealth/js/utils.js
phantomwright/stealth/js/evasions/chrome.app.js
phantomwright/stealth/js/evasions/chrome.csi.js
phantomwright/stealth/js/evasions/chrome.hairline.js
phantomwright/stealth/js/evasions/chrome.load.times.js
phantomwright/stealth/js/evasions/chrome.runtime.js
phantomwright/stealth/js/evasions/error.prototype.js
phantomwright/stealth/js/evasions/iframe.contentWindow.js
phantomwright/stealth/js/evasions/media.codecs.js
phantomwright/stealth/js/evasions/navigator.hardwareConcurrency.js
phantomwright/stealth/js/evasions/navigator.languages.js
phantomwright/stealth/js/evasions/navigator.permissions.js
phantomwright/stealth/js/evasions/navigator.platform.js
phantomwright/stealth/js/evasions/navigator.plugins.js
phantomwright/stealth/js/evasions/navigator.userAgent.js
phantomwright/stealth/js/evasions/navigator.vendor.js
phantomwright/stealth/js/evasions/webgl.vendor.js
phantomwright/sync_api/__init__.py
phantomwright/user_simulator/README.md
phantomwright/user_simulator/__init__.py
phantomwright/user_simulator/async_basic.py
phantomwright/user_simulator/async_simulator.py
phantomwright-0.1.5.dist-info/METADATA
phantomwright-0.1.5.dist-info/WHEEL
phantomwright-0.1.5.dist-info/licenses/LICENSE
phantomwright-0.1.5.dist-info/RECORD
