Metadata-Version: 2.4
Name: phantomwright
Version: 0.1.5
Summary: Bridging playwright-core patch + extending playwright API for stealth injection & user simulation
Project-URL: homepage, https://github.com/ai-microsoft/phantom-wright
Project-URL: changelog, https://github.com/ai-microsoft/phantom-wright/blob/main/CHANGELOG.md
Author-email: Hang Yin <hangyin@microsoft.com>, Daniel Wan <benyuwan@microsoft.com>
License-Expression: MIT
License-File: LICENSE
Classifier: Operating System :: OS Independent
Classifier: Programming Language :: Python :: 3
Requires-Python: >=3.9
Requires-Dist: phantomwright-driver==1.57.7
Provides-Extra: black
Requires-Dist: black>=25.9.0; extra == 'black'
Provides-Extra: dev
Requires-Dist: pytest-asyncio>=1.2.0; extra == 'dev'
Requires-Dist: pytest>=8.4.2; extra == 'dev'
